watched/__init__.py
watched/fibonacci.py
watched-0.0.0.dist-info/LICENSE
watched-0.0.0.dist-info/METADATA
watched-0.0.0.dist-info/WHEEL
watched-0.0.0.dist-info/top_level.txt
watched-0.0.0.dist-info/RECORD
