Metadata-Version: 2.1
Name: watched
Version: 0.0.0
Summary: It's like watch, but with history.
Home-page: https://github.com/chhabrakadabra/watched
Author: Abhin Chhabra
Author-email: chhabra.abhin@gmail.com
License: MIT License
Platform: UNKNOWN
Classifier: Programming Language :: Python :: 3.7
Classifier: License :: OSI Approved :: MIT License
Classifier: Operating System :: OS Independent
Requires-Python: >3.7
Provides-Extra: linter
Requires-Dist: flake8 ; extra == 'linter'
Requires-Dist: flake8-broken-line ; extra == 'linter'
Requires-Dist: flake8-builtins ; extra == 'linter'
Requires-Dist: flake8-bugbear ; extra == 'linter'
Requires-Dist: flake8-comprehensions ; extra == 'linter'
Requires-Dist: flake8-eradicate ; extra == 'linter'
Requires-Dist: flake8-pep3101 ; extra == 'linter'
Requires-Dist: flake8-print ; extra == 'linter'
Requires-Dist: flake8-quotes ; extra == 'linter'
Provides-Extra: tests
Requires-Dist: pytest ; extra == 'tests'
